pykdgrav/__init__.py
pykdgrav/kdtree.py
pykdgrav/kernel.py
pykdgrav/treewalk.py
pykdgrav-0.14.6.dist-info/LICENSE.txt
pykdgrav-0.14.6.dist-info/METADATA
pykdgrav-0.14.6.dist-info/WHEEL
pykdgrav-0.14.6.dist-info/top_level.txt
pykdgrav-0.14.6.dist-info/RECORD
