Metadata-Version: 2.1
Name: pykdgrav
Version: 0.14.6
Summary: Fast approximate gravitational force and potential calculations
Home-page: http://github.com/mikegrudic/pykdgrav
Author: Mike Grudic
Author-email: mike.grudich@gmail.com
License: MIT
Platform: UNKNOWN
